aind_ophys_utils/__init__.py
aind_ophys_utils/array_utils.py
aind_ophys_utils/dff.py
aind_ophys_utils/motion_border_utils.py
aind_ophys_utils/signal_utils.py
aind_ophys_utils/summary_images.py
aind_ophys_utils/video_utils.py
aind_ophys_utils-0.0.8.dist-info/LICENSE
aind_ophys_utils-0.0.8.dist-info/METADATA
aind_ophys_utils-0.0.8.dist-info/WHEEL
aind_ophys_utils-0.0.8.dist-info/top_level.txt
aind_ophys_utils-0.0.8.dist-info/RECORD
