Metadata-Version: 2.1
Name: aind-ophys-utils
Version: 0.0.8
Summary: Generated from aind-library-template
Author: Allen Institute for Neural Dynamics
License: MIT
Classifier: Programming Language :: Python :: 3
Requires-Python: >=3.7
License-File: LICENSE
Requires-Dist: h5py
Requires-Dist: imageio-ffmpeg
Requires-Dist: pandas
Requires-Dist: scikit-image
Requires-Dist: torch
Provides-Extra: dev
Requires-Dist: black ; extra == 'dev'
Requires-Dist: coverage ; extra == 'dev'
Requires-Dist: flake8 ; extra == 'dev'
Requires-Dist: interrogate ; extra == 'dev'
Requires-Dist: isort ; extra == 'dev'
Requires-Dist: Sphinx ; extra == 'dev'
Requires-Dist: furo ; extra == 'dev'
Requires-Dist: pytest ; extra == 'dev'
